fsutils/__init__.py
fsutils/logs.py
fsutils-0.6.0.data/scripts/fs_slice
fsutils-0.6.0.data/scripts/fs_slice_subjects
fsutils-0.6.0.data/scripts/fs_status
fsutils-0.6.0.dist-info/COPYING
fsutils-0.6.0.dist-info/METADATA
fsutils-0.6.0.dist-info/WHEEL
fsutils-0.6.0.dist-info/top_level.txt
fsutils-0.6.0.dist-info/RECORD
