Metadata-Version: 2.1
Name: fsutils
Version: 0.6.0
Summary: Utilities for working with FreeSurfer data
Home-page: https://github.com/chaselgrove/fsutils
Author: Christian Haselgrove
Author-email: christian.haselgrove@umassmed.edu
License: BSD license
Platform: UNKNOWN
Classifier: Development Status :: 3 - Alpha
Classifier: Environment :: Console
Classifier: Intended Audience :: Science/Research
Classifier: License :: OSI Approved :: BSD License
Classifier: Operating System :: OS Independent
Classifier: Programming Language :: Python
Classifier: Topic :: Scientific/Engineering
Requires-Dist: argparse
Requires-Dist: python-dateutil
Requires-Dist: numpy
Requires-Dist: nibabel
Requires-Dist: Pillow
